passiogo/__init__.py
tests/__init__.py
tests/test_main.py
passiogo_updated-0.2.2.dist-info/LICENSE
passiogo_updated-0.2.2.dist-info/METADATA
passiogo_updated-0.2.2.dist-info/WHEEL
passiogo_updated-0.2.2.dist-info/top_level.txt
passiogo_updated-0.2.2.dist-info/RECORD
