Metadata-Version: 2.2
Name: PassioGo_updated
Version: 0.2.2
Summary: An unofficial API for Passio Go
Home-page: https://github.com/athuler/PassioGo
Author: Andrei Thuler
Author-email: info@andreithuler.com
Project-URL: Documentation, https://passiogo.readthedocs.io/
Project-URL: GitHub, https://github.com/athuler/PassioGo
Project-URL: Sponsor, https://github.com/sponsors/athuler
Project-URL: Changelog, https://github.com/athuler/PassioGo/blob/main/CHANGELOG.md
Classifier: Programming Language :: Python :: 3
Classifier: License :: OSI Approved :: MIT License
Classifier: Operating System :: OS Independent
Requires-Python: >=3.7
License-File: LICENSE
Requires-Dist: requests
Dynamic: author
Dynamic: author-email
Dynamic: classifier
Dynamic: description
Dynamic: description-content-type
Dynamic: home-page
Dynamic: project-url
Dynamic: requires-dist
Dynamic: requires-python
Dynamic: summary
